setup.py
EasySuperPrint.egg-info/PKG-INFO
EasySuperPrint.egg-info/SOURCES.txt
EasySuperPrint.egg-info/dependency_links.txt
EasySuperPrint.egg-info/top_level.txt
easysuperprint/__init__.py