Metadata-Version: 2.1
Name: EasySuperPrint
Version: 1.0
Summary: Python color utilities and other terminal related stuff coming soon.
Author: JustAnEric
Author-email: dev@justaneric.co
